typeinc_mini/__init__.py
typeinc_mini/main.py
typeinc_mini/wordlist.txt
typeinc_mini/configurations/input_config.py
typeinc_mini/configurations/mainscreen.py
typeinc_mini/configurations/result.py
typeinc_mini/configurations/text_gen.py
typeinc_mini/configurations/ui.py
typeinc_mini/scores/highscore.py
typeinc_mini/scores/scores.json
typeinc_mini-1.0.0.dist-info/LICENSE.md
typeinc_mini-1.0.0.dist-info/METADATA
typeinc_mini-1.0.0.dist-info/WHEEL
typeinc_mini-1.0.0.dist-info/entry_points.txt
typeinc_mini-1.0.0.dist-info/top_level.txt
typeinc_mini-1.0.0.dist-info/RECORD
