Metadata-Version: 2.1
Name: typeinc-mini
Version: 1.0.0
Summary: Typeinc-mini, a miniature version of Typeinc, an ncurses based tool, is your goto terminal tool to play around with your typing speed with various difficulty levels.
Home-page: https://github.com/AnirudhG07/Typeinc-mini
Author: Anirudh Gupta
Keywords: terminal,typing speed test,typing,CLI
Classifier: Development Status :: 5 - Production/Stable
Classifier: Intended Audience :: Developers
Classifier: Programming Language :: Python :: 3.11
Classifier: Programming Language :: Python :: 3.12
Classifier: Topic :: Games/Entertainment
Classifier: License :: OSI Approved :: Apache Software License
Classifier: Operating System :: POSIX
Classifier: Operating System :: MacOS
Classifier: Operating System :: Microsoft :: Windows
Requires-Python: >=3.11
License-File: LICENSE.md
Requires-Dist: setuptools
Requires-Dist: wheel
Requires-Dist: twine
